gofigr/__init__.py
gofigr/_version.py
gofigr/annotators.py
gofigr/databricks.py
gofigr/exceptions.py
gofigr/gfconfig.py
gofigr/jupyter.py
gofigr/models.py
gofigr/profile.py
gofigr/proxy.py
gofigr/publisher.py
gofigr/trap.py
gofigr/utils.py
gofigr/watermarks.py
gofigr/widget.py
gofigr/backends/__init__.py
gofigr/backends/matplotlib.py
gofigr/backends/plotly.py
gofigr/backends/plotnine.py
gofigr/backends/py3dmol.py
gofigr/lite/__init__.py
gofigr/resources/FreeMono.ttf
gofigr/resources/__init__.py
gofigr/resources/copy_image.js
gofigr/resources/copy_text.js
gofigr/resources/gofigr.css
gofigr/resources/loader.js
gofigr/resources/loader.py
gofigr/resources/logo_large.png
gofigr/resources/logo_small.png
gofigr-1.3.2.data/data/share/jupyter/labextensions/gofigr/package.json
gofigr-1.3.2.data/data/share/jupyter/labextensions/gofigr/static/101.fb896cced2cfb5282373.js
gofigr-1.3.2.data/data/share/jupyter/labextensions/gofigr/static/728.085f05ac1abc04d3715e.js
gofigr-1.3.2.data/data/share/jupyter/labextensions/gofigr/static/remoteEntry.8c699de6bff8c56e1c58.js
gofigr-1.3.2.data/data/share/jupyter/labextensions/gofigr/static/style.js
gofigr-1.3.2.data/data/share/jupyter/labextensions/gofigr/static/third-party-licenses.json
gofigr-1.3.2.data/data/share/jupyter/labextensions/gofigr/install.json
gofigr-1.3.2.dist-info/METADATA
gofigr-1.3.2.dist-info/WHEEL
gofigr-1.3.2.dist-info/entry_points.txt
gofigr-1.3.2.dist-info/licenses/LICENSE
gofigr-1.3.2.dist-info/RECORD
