Metadata-Version: 2.4
Name: gofigr
Version: 1.3.2
Summary: GoFigr client library
Project-URL: Homepage, https://www.gofigr.io
Project-URL: Documentation, https://gofigr.io/docs/gofigr-python/1.3.2/
Author-email: Maciej Pacula <maciej@gofigr.io>
License: Copyright 2022-2025 Flagstaff Solutions, LLC
License-File: LICENSE
Keywords: data,plotting,reproducibility,science,version control,visualization
Classifier: Framework :: Jupyter
Classifier: Framework :: Jupyter :: JupyterLab
Classifier: Framework :: Jupyter :: JupyterLab :: 4
Classifier: Framework :: Jupyter :: JupyterLab :: Extensions
Classifier: Framework :: Jupyter :: JupyterLab :: Extensions :: Prebuilt
Classifier: License :: OSI Approved :: BSD License
Classifier: License :: OSI Approved :: MIT License
Classifier: Programming Language :: Python
Classifier: Programming Language :: Python :: 3
Classifier: Programming Language :: Python :: 3.9
Classifier: Programming Language :: Python :: 3.10
Classifier: Programming Language :: Python :: 3.11
Classifier: Programming Language :: Python :: 3.12
Classifier: Programming Language :: Python :: 3.13
Requires-Python: >=3.8
Requires-Dist: blake3
Requires-Dist: dateutils
Requires-Dist: gitpython
Requires-Dist: humanize
Requires-Dist: ipython
Requires-Dist: ipywidgets>=8.1.0
Requires-Dist: kaleido
Requires-Dist: matplotlib
Requires-Dist: nest-asyncio
Requires-Dist: numpy
Requires-Dist: pandas
Requires-Dist: pillow
Requires-Dist: plotly
Requires-Dist: pypng
Requires-Dist: pyqrcode
Requires-Dist: python-dateutil
Requires-Dist: requests
Provides-Extra: databricks
Requires-Dist: databricks-sdk; extra == 'databricks'
Provides-Extra: dev
Requires-Dist: build; extra == 'dev'
Requires-Dist: bumpver; extra == 'dev'
Requires-Dist: flake8; extra == 'dev'
Requires-Dist: hatch; extra == 'dev'
Requires-Dist: hatch-nodejs-version; extra == 'dev'
Requires-Dist: hatchling; extra == 'dev'
Requires-Dist: html2image; extra == 'dev'
Requires-Dist: jupyterlab; extra == 'dev'
Requires-Dist: matplotlib; extra == 'dev'
Requires-Dist: openpyxl; extra == 'dev'
Requires-Dist: pip-tools; extra == 'dev'
Requires-Dist: plotnine; extra == 'dev'
Requires-Dist: py3dmol; extra == 'dev'
Requires-Dist: pylint<4.0.0; extra == 'dev'
Requires-Dist: seaborn; extra == 'dev'
Requires-Dist: selenium; extra == 'dev'
Requires-Dist: sphinx; extra == 'dev'
Requires-Dist: sphinx-rtd-theme; extra == 'dev'
Requires-Dist: sphinxcontrib-jquery; extra == 'dev'
Requires-Dist: teamcity-messages; extra == 'dev'
Requires-Dist: tqdm; extra == 'dev'
Requires-Dist: twine; extra == 'dev'
Requires-Dist: webdriver-manager; extra == 'dev'
